nginx_quickdeploy/__init__.py
nginx_quickdeploy/file_operations.py
nginx_quickdeploy/main.py
nginx_quickdeploy/misc.py
nginx_quickdeploy/system_operations.py
nginx_quickdeploy/validation.py
nginx_quickdeploy/version.json
nginx_quickdeploy-0.4.2.data/data/nginx_quickdeploy/version.json
nginx_quickdeploy-0.4.2.dist-info/METADATA
nginx_quickdeploy-0.4.2.dist-info/WHEEL
nginx_quickdeploy-0.4.2.dist-info/entry_points.txt
nginx_quickdeploy-0.4.2.dist-info/top_level.txt
nginx_quickdeploy-0.4.2.dist-info/RECORD
