Metadata-Version: 2.1
Name: nginx-quickdeploy
Version: 0.4.2
Summary: Nginx Quickdeploy
Home-page: https://github.com/regmibijay/nginx-quickdeploy
Author: Bijay Regmi
Author-email: github@regdelivery.de
License: MIT
Platform: UNKNOWN
Classifier: Programming Language :: Python :: 3
Classifier: License :: OSI Approved :: MIT License
Classifier: Operating System :: OS Independent
Requires-Python: >=3.6
